icinga_slack/__init__.py
icinga_slack/__main__.py
icinga_slack/webhook.py
icinga_slack_webhook-2.1.1.dist-info/LICENSE
icinga_slack_webhook-2.1.1.dist-info/METADATA
icinga_slack_webhook-2.1.1.dist-info/WHEEL
icinga_slack_webhook-2.1.1.dist-info/entry_points.txt
icinga_slack_webhook-2.1.1.dist-info/top_level.txt
icinga_slack_webhook-2.1.1.dist-info/RECORD
