Metadata-Version: 2.1
Name: icinga-slack-webhook
Version: 2.1.1
Summary: icinga-slack-webhook: A notifier from Icinga to Slack
Home-page: https://github.com/samjsharpe/icinga_slack_webhook
Author: Sam Sharpe
Author-email: sam.sharpe@digital.cabinet-office.gov.uk
Maintainer: Sam Sharpe
License: MIT
Platform: UNKNOWN
